data_validation/__init__.py
data_validation/__main__.py
data_validation/app.py
data_validation/cli_tools.py
data_validation/client_info.py
data_validation/clients.py
data_validation/combiner.py
data_validation/config_manager.py
data_validation/consts.py
data_validation/data_validation.py
data_validation/exceptions.py
data_validation/find_tables.py
data_validation/gcs_helper.py
data_validation/jellyfish_distance.py
data_validation/metadata.py
data_validation/partition_builder.py
data_validation/raw_query.py
data_validation/schema_validation.py
data_validation/secret_manager.py
data_validation/state_manager.py
data_validation/util.py
data_validation/validation_builder.py
data_validation/query_builder/__init__.py
data_validation/query_builder/partition_row_builder.py
data_validation/query_builder/query_builder.py
data_validation/query_builder/random_row_builder.py
data_validation/result_handlers/__init__.py
data_validation/result_handlers/base_backend.py
data_validation/result_handlers/bigquery.py
data_validation/result_handlers/factory.py
data_validation/result_handlers/postgres.py
data_validation/result_handlers/text.py
google_pso_data_validator-8.4.0.dist-info/licenses/LICENSE
third_party/ibis/ibis_addon/__init__.py
third_party/ibis/ibis_addon/api.py
third_party/ibis/ibis_addon/operations.py
third_party/ibis/ibis_bigquery/__init__.py
third_party/ibis/ibis_bigquery/api.py
third_party/ibis/ibis_bigquery/registry.py
third_party/ibis/ibis_cloud_spanner/__init__.py
third_party/ibis/ibis_cloud_spanner/api.py
third_party/ibis/ibis_cloud_spanner/client.py
third_party/ibis/ibis_cloud_spanner/compiler.py
third_party/ibis/ibis_cloud_spanner/datatypes.py
third_party/ibis/ibis_cloud_spanner/registry.py
third_party/ibis/ibis_cloud_spanner/to_pandas.py
third_party/ibis/ibis_cloud_spanner/tests/__init__.py
third_party/ibis/ibis_cloud_spanner/tests/conftest.py
third_party/ibis/ibis_db2/__init__.py
third_party/ibis/ibis_db2/api.py
third_party/ibis/ibis_db2/compiler.py
third_party/ibis/ibis_db2/datatypes.py
google_pso_data_validator-8.4.0.dist-info/METADATA
google_pso_data_validator-8.4.0.dist-info/WHEEL
google_pso_data_validator-8.4.0.dist-info/entry_points.txt
google_pso_data_validator-8.4.0.dist-info/top_level.txt
google_pso_data_validator-8.4.0.dist-info/RECORD
