Metadata-Version: 2.4
Name: google-pso-data-validator
Version: 8.4.0
Summary: A package to enable easy data validation
Author: PSO DVT Engineering team
Author-email: data-validator-eng@google.com
Classifier: Development Status :: 4 - Beta
Classifier: License :: OSI Approved :: Apache Software License
Classifier: Programming Language :: Python
Classifier: Programming Language :: Python :: 3.9
Classifier: Programming Language :: Python :: 3.10
Classifier: Programming Language :: Python :: 3.11
Classifier: Operating System :: OS Independent
Requires-Python: >=3.9
License-File: LICENSE
Requires-Dist: Flask>=2.2
Requires-Dist: fsspec
Requires-Dist: google-api-python-client>=2.144.0
Requires-Dist: google-cloud-bigquery>=3.25.0
Requires-Dist: google-cloud-bigquery-storage>=2.26.0
Requires-Dist: google-cloud-secret-manager>=2.20.2
Requires-Dist: google-cloud-spanner>=3.49.1
Requires-Dist: google-cloud-storage>=2.18.2
Requires-Dist: ibis-framework==5.1.0
Requires-Dist: impyla>=0.19.0
Requires-Dist: jellyfish>=1.1.0
Requires-Dist: pandas
Requires-Dist: parsy>=2.1
Requires-Dist: psycopg2-binary>=2.9.9
Requires-Dist: pyarrow
Requires-Dist: pydata-google-auth>=1.8.2
Requires-Dist: PyMySQL>=1.1.1
Requires-Dist: PyYAML>=6.0.2
Requires-Dist: SQLAlchemy==2.0.41
Requires-Dist: tabulate>=0.9.0
Provides-Extra: apache-airflow
Requires-Dist: 1.10.11; extra == "apache-airflow"
Provides-Extra: pyspark
Requires-Dist: 3.0.0; extra == "pyspark"
Provides-Extra: develop
Requires-Dist: black==22.3.0; extra == "develop"
Requires-Dist: flake8; extra == "develop"
Requires-Dist: freezegun; extra == "develop"
Requires-Dist: pyfakefs; extra == "develop"
Requires-Dist: pytest; extra == "develop"
Requires-Dist: pytest-cov; extra == "develop"
Requires-Dist: pytest-rerunfailures; extra == "develop"
Requires-Dist: pytest-timeout; extra == "develop"
Dynamic: author
Dynamic: author-email
Dynamic: classifier
Dynamic: description
Dynamic: description-content-type
Dynamic: license-file
Dynamic: provides-extra
Dynamic: requires-dist
Dynamic: requires-python
Dynamic: summary
